gj_meta_mcp/__init__.py
gj_meta_mcp/digital_human_generator.py
gj_meta_mcp/random_helper.py
gj_meta_mcp/server.py
guiji_meta_mcp-0.0.3.dist-info/licenses/LICENSE
guiji_meta_mcp-0.0.3.dist-info/METADATA
guiji_meta_mcp-0.0.3.dist-info/WHEEL
guiji_meta_mcp-0.0.3.dist-info/entry_points.txt
guiji_meta_mcp-0.0.3.dist-info/top_level.txt
guiji_meta_mcp-0.0.3.dist-info/RECORD
