Metadata-Version: 2.4
Name: guiji_meta_mcp
Version: 0.0.3
Summary: create meta human by guiji api.
Author-email: weichi <weichi@guiji.ai>
License: MIT License
Keywords: guiji,mcp,create-meta
Classifier: Development Status :: 4 - Beta
Classifier: Intended Audience :: Developers
Classifier: License :: OSI Approved :: MIT License
Classifier: Programming Language :: Python :: 3
Classifier: Programming Language :: Python :: 3.10
Classifier: Programming Language :: Python :: 3.11
Classifier: Programming Language :: Python :: 3.12
Requires-Python: >=3.10
License-File: LICENSE
Requires-Dist: mcp>=1.6.0
Requires-Dist: aiohttp>=3.11.16
Requires-Dist: fastapi==0.109.2
Requires-Dist: python-dotenv~=1.0.1
Requires-Dist: httpx==0.28.1
Provides-Extra: dev
Requires-Dist: pre-commit==3.6.2; extra == "dev"
Requires-Dist: fastmcp==0.4.1; extra == "dev"
Requires-Dist: pytest==8.0.0; extra == "dev"
Requires-Dist: pytest-cov==4.1.0; extra == "dev"
Requires-Dist: build>=1.0.3; extra == "dev"
Dynamic: license-file
